LICENSE
MANIFEST.in
README.rst
setup.py
TelethonGoblenusTest.egg-info/PKG-INFO
TelethonGoblenusTest.egg-info/SOURCES.txt
TelethonGoblenusTest.egg-info/dependency_links.txt
TelethonGoblenusTest.egg-info/requires.txt
TelethonGoblenusTest.egg-info/top_level.txt
telethon/__init__.py
telethon/helpers.py
telethon/telegram_bare_client.py
telethon/telegram_client.py
telethon/update_state.py
telethon/utils.py
telethon/version.py
telethon/crypto/__init__.py
telethon/crypto/aes.py
telethon/crypto/aes_ctr.py
telethon/crypto/auth_key.py
telethon/crypto/cdn_decrypter.py
telethon/crypto/factorization.py
telethon/crypto/libssl.py
telethon/crypto/rsa.py
telethon/errors/__init__.py
telethon/errors/common.py
telethon/errors/rpc_base_errors.py
telethon/extensions/__init__.py
telethon/extensions/binary_reader.py
telethon/extensions/markdown.py
telethon/extensions/tcp_client.py
telethon/network/__init__.py
telethon/network/authenticator.py
telethon/network/connection.py
telethon/network/mtproto_plain_sender.py
telethon/network/mtproto_sender.py
telethon/tl/__init__.py
telethon/tl/entity_database.py
telethon/tl/gzip_packed.py
telethon/tl/message_container.py
telethon/tl/session.py
telethon/tl/tl_message.py
telethon/tl/tlobject.py
telethon/tl/custom/__init__.py
telethon/tl/custom/draft.py
telethon_generator/parser/__init__.py
telethon_generator/parser/source_builder.py
telethon_generator/parser/tl_object.py
telethon_generator/parser/tl_parser.py