Metadata-Version: 1.1
Name: TelethonGoblenusTest
Version: 0.15.5
Summary: Full-featured Telegram client library for Python 3
Home-page: https://github.com/LonamiWebs/Telethon
Author: Lonami Exo
Author-email: totufals@hotmail.com
License: MIT
Download-URL: https://github.com/LonamiWebs/Telethon/releases
Keywords: telegram api chat client library messaging mtproto
Platform: UNKNOWN
Classifier: Development Status :: 3 - Alpha
Classifier: Intended Audience :: Developers
Classifier: Topic :: Communications :: Chat
Classifier: License :: OSI Approved :: MIT License
Classifier: Programming Language :: Python :: 3
Classifier: Programming Language :: Python :: 3.3
Classifier: Programming Language :: Python :: 3.4
Classifier: Programming Language :: Python :: 3.5
Classifier: Programming Language :: Python :: 3.6
